liam_tools/AESCipher.py
liam_tools/AESECB.py
liam_tools/B64.py
liam_tools/BackgroudProcess.py
liam_tools/CPImg.py
liam_tools/CPVideo.py
liam_tools/Captcha.py
liam_tools/DBTool.py
liam_tools/EBQueue.py
liam_tools/Github.py
liam_tools/Hash.py
liam_tools/HttpUtils.py
liam_tools/Ip.py
liam_tools/SenderBase.py
liam_tools/__init__.py
liam_tools/env.py
liam_tools/kvp.py
liam_tools/path.py
liam_tools/pl.py
liam_tools/udict.py
liam_tools/ustr.py
liam_tools-0.1.2.dist-info/LICENSE
liam_tools-0.1.2.dist-info/METADATA
liam_tools-0.1.2.dist-info/WHEEL
liam_tools-0.1.2.dist-info/top_level.txt
liam_tools-0.1.2.dist-info/RECORD
