Metadata-Version: 2.1
Name: liam-tools
Version: 0.1.2
Summary: python base tools
Author-email: Liam Davis <respondnet@gmail.com>
Project-URL: Homepage, https://github.com/yourusername/yourrepo
Classifier: Programming Language :: Python :: 3
Classifier: License :: OSI Approved :: MIT License
Classifier: Operating System :: OS Independent
Requires-Python: >=3.7
License-File: LICENSE
